MANIFEST.in
README.rst
setup.py
crunner/__init__.py
crunner/config.py
crunner/event.py
crunner/logger.py
crunner/notifier.py
crunner/runner.py
crunner/watcher.py
crunner.egg-info/PKG-INFO
crunner.egg-info/SOURCES.txt
crunner.egg-info/dependency_links.txt
crunner.egg-info/requires.txt
crunner.egg-info/top_level.txt
crunner/images/nok.png
crunner/images/ok.png
script/crun
test/test_config.py
test/test_event.py
test/test_notifier.py
test/test_runner.py
test/test_watcher.py