Metadata-Version: 1.0
Name: crunner
Version: 0.2.2
Summary: Continues test runner.
Home-page: http://pchomik.github.io/crunner/
Author: Pawel Chomicki
Author-email: pawel.chomicki@gmail.com
License: UNKNOWN
Platform: UNKNOWN
